LICENSE
README.md
setup.py
src/sqlvana/__init__.py
src/sqlvana/local.py
src/sqlvana/remote.py
src/sqlvana/utils.py
src/sqlvana.egg-info/PKG-INFO
src/sqlvana.egg-info/SOURCES.txt
src/sqlvana.egg-info/dependency_links.txt
src/sqlvana.egg-info/requires.txt
src/sqlvana.egg-info/top_level.txt
src/sqlvana/ZhipuAI/ZhipuAI_Chat.py
src/sqlvana/ZhipuAI/ZhipuAI_embeddings.py
src/sqlvana/ZhipuAI/__init__.py
src/sqlvana/anthropic/__init__.py
src/sqlvana/anthropic/anthropic_chat.py
src/sqlvana/base/__init__.py
src/sqlvana/base/base.py
src/sqlvana/chromadb/__init__.py
src/sqlvana/chromadb/chromadb_vector.py
src/sqlvana/exceptions/__init__.py
src/sqlvana/flask/__init__.py
src/sqlvana/flask/assets.py
src/sqlvana/flask/auth.py
src/sqlvana/google/__init__.py
src/sqlvana/google/gemini_chat.py
src/sqlvana/marqo/__init__.py
src/sqlvana/marqo/marqo.py
src/sqlvana/mistral/__init__.py
src/sqlvana/mistral/mistral.py
src/sqlvana/ollama/__init__.py
src/sqlvana/ollama/ollama.py
src/sqlvana/openai/__init__.py
src/sqlvana/openai/openai_chat.py
src/sqlvana/openai/openai_embeddings.py
src/sqlvana/qdrant/__init__.py
src/sqlvana/qdrant/qdrant.py
src/sqlvana/types/__init__.py
src/sqlvana/vannadb/__init__.py
src/sqlvana/vannadb/vannadb_vector.py
src/sqlvana/vllm/__init__.py
src/sqlvana/vllm/vllm.py
tests/test_imports.py
tests/test_sqlvana.py